avplayer/__init__.py
avplayer/__main__.py
avplayer/arguments.py
avplayer/avconfig.py
avplayer/entrypoint.py
avplayer/variables.py
avplayer/aio/__init__.py
avplayer/aio/run.py
avplayer/apps/__init__.py
avplayer/apps/base/__init__.py
avplayer/apps/base/async_av_app.py
avplayer/apps/base/async_av_tk.py
avplayer/apps/base/async_cv_app.py
avplayer/apps/base/av_app.py
avplayer/apps/base/base.py
avplayer/apps/defaults/__init__.py
avplayer/apps/defaults/aio.py
avplayer/apps/defaults/cv.py
avplayer/apps/defaults/io.py
avplayer/apps/defaults/tk.py
avplayer/apps/interface/__init__.py
avplayer/apps/interface/av_interface.py
avplayer/av/__init__.py
avplayer/av/av_flags.py
avplayer/av/av_hls_options.py
avplayer/av/av_io.py
avplayer/av/av_logging.py
avplayer/av/av_modules.py
avplayer/av/av_open.py
avplayer/av/av_options.py
avplayer/av/av_probe.py
avplayer/debug/__init__.py
avplayer/debug/avg_stat.py
avplayer/ffmpeg/__init__.py
avplayer/ffmpeg/ffmpeg.py
avplayer/ffmpeg/ffmpeg_formats.py
avplayer/ffmpeg/ffmpeg_pix_fmts.py
avplayer/logging/__init__.py
avplayer/logging/colored_formatter.py
avplayer/logging/logging.py
avplayer/m3u/__init__.py
avplayer/m3u/m3u_builder.py
avplayer/m3u/m3u_tags.py
examples/__init__.py
examples/cv2_example.py
avplayer-1.9.1.dist-info/LICENSE
avplayer-1.9.1.dist-info/METADATA
avplayer-1.9.1.dist-info/WHEEL
avplayer-1.9.1.dist-info/entry_points.txt
avplayer-1.9.1.dist-info/top_level.txt
avplayer-1.9.1.dist-info/RECORD
