Metadata-Version: 2.1
Name: avplayer
Version: 1.9.1
Summary: PyAV Media Player
Home-page: https://github.com/osom8979/avplayer
Author: zer0
Author-email: osom8979@gmail.com
Maintainer: zer0
Maintainer-email: osom8979@gmail.com
License: MIT License
Project-URL: GitHub: issues, https://github.com/osom8979/avplayer/issues
Project-URL: GitHub: repo, https://github.com/osom8979/avplayer
Platform: UNKNOWN
Classifier: Development Status :: 4 - Beta
Classifier: Framework :: AsyncIO
Classifier: Intended Audience :: Developers
Classifier: Operating System :: OS Independent
Classifier: Programming Language :: Python
Classifier: Programming Language :: Python :: 3.9
Classifier: Topic :: Software Development
Classifier: Topic :: Utilities
Classifier: License :: OSI Approved :: MIT License
Requires-Python: >=3.9
License-File: LICENSE
Requires-Dist: av
Requires-Dist: coloredlogs
Requires-Dist: numpy
Requires-Dist: overrides
Provides-Extra: pillow
Requires-Dist: Pillow; extra == "pillow"
